ovos_skill_laugh/__init__.py
ovos_skill_laugh/package.json
ovos_skill_laugh/settingsmeta.json
ovos_skill_laugh/skill.json
ovos_skill_laugh/version.py
ovos_skill_laugh/gui/all/0.jpg
ovos_skill_laugh/gui/all/1.jpg
ovos_skill_laugh/gui/all/2.jpg
ovos_skill_laugh/gui/all/3.jpg
ovos_skill_laugh/locale/ca-es/dialog/cancel.dialog
ovos_skill_laugh/locale/ca-es/dialog/cancel_fail.dialog
ovos_skill_laugh/locale/ca-es/dialog/maybe.dialog
ovos_skill_laugh/locale/ca-es/dialog/yes.dialog
ovos_skill_laugh/locale/ca-es/vocab/Laugh.intent
ovos_skill_laugh/locale/ca-es/vocab/RandomLaugh.intent
ovos_skill_laugh/locale/ca-es/vocab/Stop.voc
ovos_skill_laugh/locale/ca-es/vocab/haunted.intent
ovos_skill_laugh/locale/da-dk/dialog/cancel.dialog
ovos_skill_laugh/locale/da-dk/dialog/cancel_fail.dialog
ovos_skill_laugh/locale/da-dk/dialog/maybe.dialog
ovos_skill_laugh/locale/da-dk/dialog/yes.dialog
ovos_skill_laugh/locale/da-dk/vocab/Laugh.intent
ovos_skill_laugh/locale/da-dk/vocab/Laugh.voc
ovos_skill_laugh/locale/da-dk/vocab/RandomLaugh.intent
ovos_skill_laugh/locale/da-dk/vocab/Stop.voc
ovos_skill_laugh/locale/da-dk/vocab/haunted.intent
ovos_skill_laugh/locale/de-de/dialog/cancel.dialog
ovos_skill_laugh/locale/de-de/dialog/cancel_fail.dialog
ovos_skill_laugh/locale/de-de/dialog/maybe.dialog
ovos_skill_laugh/locale/de-de/dialog/yes.dialog
ovos_skill_laugh/locale/de-de/vocab/Laugh.intent
ovos_skill_laugh/locale/de-de/vocab/Laugh.voc
ovos_skill_laugh/locale/de-de/vocab/RandomLaugh.intent
ovos_skill_laugh/locale/de-de/vocab/Stop.voc
ovos_skill_laugh/locale/de-de/vocab/haunted.intent
ovos_skill_laugh/locale/el-gr/dialog/cancel.dialog
ovos_skill_laugh/locale/el-gr/dialog/cancel_fail.dialog
ovos_skill_laugh/locale/el-gr/vocab/Laugh.intent
ovos_skill_laugh/locale/el-gr/vocab/Laugh.voc
ovos_skill_laugh/locale/el-gr/vocab/RandomLaugh.intent
ovos_skill_laugh/locale/el-gr/vocab/Stop.voc
ovos_skill_laugh/locale/en-us/dialog/cancel.dialog
ovos_skill_laugh/locale/en-us/dialog/cancel_fail.dialog
ovos_skill_laugh-0.2.3.dist-info/LICENSE
ovos_skill_laugh-0.2.3.dist-info/METADATA
ovos_skill_laugh-0.2.3.dist-info/WHEEL
ovos_skill_laugh-0.2.3.dist-info/entry_points.txt
ovos_skill_laugh-0.2.3.dist-info/top_level.txt
ovos_skill_laugh-0.2.3.dist-info/RECORD
