Metadata-Version: 2.1
Name: ovos-skill-laugh
Version: 0.2.3
Home-page: https://github.com/openvoiceos/ovos-skill-laugh
Author: OpenVoiceOS
Author-email: jarbas@openvoiceos.com
License: Apache-2.0
Keywords: ovos skill voice assistant
License-File: LICENSE
Requires-Dist: ovos-utils
Requires-Dist: ovos-workshop
Requires-Dist: ovos-plugin-manager
Requires-Dist: ovos-audio
Requires-Dist: ovos-bus-client>=1.0.1
Provides-Extra: test
Requires-Dist: pytest; extra == "test"
Requires-Dist: pytest-cov; extra == "test"
